{
  "face": {
    "structure": "sharp-featured with high cheekbones and a slightly pointed chin, projecting a sense of acute awareness",
    "eyes": {
      "shape": "narrow almond-shaped with a slight upward tilt",
      "color": "piercing dark brown with lighter golden flecks",
      "details": [
        "high contrast with sharp highlights near the inner corners",
        "thin, dark eyebrows angled to enhance a calculating gaze"
      ],
      "expression_effect": "attentive and discerning, often appraising"
    },
    "expression": "subtly guarded, with a hint of bemusement around the lips",
    "skin": {
      "tone": "medium with cool, olive undertones",
      "undertone": "faint greenish-gold that adds depth and complexity",
      "texture": "smooth with a hint of natural sheen, reflecting light minimally",
      "rendering_notes": "emphasize a matte finish to highlight facial features effectively"
    }
  },
  "character": {
    "hair": {
      "color": "deep black with subtle dark blue highlights",
      "style": "neatly styled with a side part and layered strands",
      "flow": "straight and sleek, with strands occasionally drifting over the forehead",
      "details": [
        "fringe slightly tousled for a casual look",
        "lightly textured ends that soften the overall appearance"
      ]
    },
    "aura": "a quiet confidence underscoring a sense of inner depth and complexity"
  },
  "outfit": {
    "base": "a sleek, modern jacket with minimalist design",
    "design": "clean lines with subtle geometric patterns in dark blue tones",
    "details": [
      "silver zipper running asymmetrically across the chest",
      "fitted cuffs with fine stitching"
    ],
    "fit": "tailored but comfortable, allowing free movement without excess material"
  },
  "composition": {
    "framing": "medium shot focusing from the waist up to capture intensity",
    "pose": "standing with one hand casually in a pocket, the other slightly raised as if poised to make a point",
    "gesture": "tilted head, eyes locked forward, projecting engagement and subtle challenge"
  },
  "background": {
    "type": "abstract cityscape",
    "color_palette": "slate grey with hints of neon blues and yellows",
    "details": "blurry lights suggesting a vibrant and bustling metropolis",
    "rules": "avoid excessive detail to maintain the focus on the character while reinforcing the urban strategist theme"
  }
}